Metadata-Version: 1.0
Name: smalltools
Version: 0.6.1
Summary: Something simple tools in it.
Home-page: https://github.com/badpasta/smalltools
Author: Badpasta
Author-email: beforget@hotmail.com
License: UNKNOWN
Platform: UNKNOWN
